pytorchlab-0.0.1.dist-info/METADATA
pytorchlab-0.0.1.dist-info/WHEEL
pytorchlab-0.0.1.dist-info/licenses/LICENSE
pytorchlab/__init__.py
pytorchlab/callbacks/__init__.py
pytorchlab/datamodules/__init__.py
pytorchlab/datamodules/basic.py
pytorchlab/datamodules/vision.py
pytorchlab/datasets/__init__.py
pytorchlab/losses/__init__.py
pytorchlab/metrics/__init__.py
pytorchlab/models/__init__.py
pytorchlab/optimizers/__init__.py
pytorchlab/transforms/__init__.py
pytorchlab/utils/__init__.py
pytorchlab/utils/data.py
pytorchlab-0.0.1.dist-info/RECORD
